QALU/__init__.py
QALU-0.3rc0.dist-info/LICENSE
QALU-0.3rc0.dist-info/METADATA
QALU-0.3rc0.dist-info/WHEEL
QALU-0.3rc0.dist-info/top_level.txt
QALU-0.3rc0.dist-info/RECORD
