Metadata-Version: 2.1
Name: QALU
Version: 0.3rc0
Summary: Quantum Arithmetic Logic Units
Author-email: Ali Hakim Taskiran <alihakimxyz@gmail.com>
License: GNU GENERAL PUBLIC LICENSE
Project-URL: Homepage, https://github.com/QArchs/QALU
Project-URL: Bug Tracker, https://github.com/QArchs/QALU/issues
Classifier: Programming Language :: Python :: 3
Classifier: License :: OSI Approved :: MIT License
Classifier: Operating System :: OS Independent
Requires-Python: >=3.8
License-File: LICENSE
